my_ctools/__init__.py
my_ctools/cal_all_largest_indicators.cpython-38-aarch64-linux-gnu.so
my_ctools/cal_all_longest_indicators.cpython-38-aarch64-linux-gnu.so
my_ctools/cal_cpr.cpython-38-aarch64-linux-gnu.so
my_ctools/cal_longest_dd_recover.cpython-38-aarch64-linux-gnu.so
my_ctools/cal_max_dd.cpython-38-aarch64-linux-gnu.so
my_ctools/cal_rolling_gain_loss.cpython-38-aarch64-linux-gnu.so
my_ctools-0.1.8.dist-info/METADATA
my_ctools-0.1.8.dist-info/WHEEL
my_ctools-0.1.8.dist-info/top_level.txt
my_ctools-0.1.8.dist-info/RECORD
