Metadata-Version: 2.1
Name: my_ctools
Version: 0.1.8
Summary: Fast C++ indicators for fund analytics
Author: KevinCJM
Requires-Python: >=3.8
